frapars/constants/__init__.py
frapars/constants/data.py
frapars/constants/france_deps.py
frapars/constants/insee.py
frapars/constants/municipalities.py
frapars/constants/postcodes.py
frapars/constants/regex.py
frapars/constants/words.py
frapars/data/insee_file.csv
frapars/examples/main.py
frapars/functions/__init__.py
frapars/functions/addresses.py
frapars/functions/clean_str.py
frapars/functions/file_parser.py
frapars/helper/__init__.py
frapars/helper/formatter.py
frapars/models/__init__.py
frapars/models/address_result.py
frapars-0.2.6.dist-info/LICENSE
frapars-0.2.6.dist-info/METADATA
frapars-0.2.6.dist-info/WHEEL
frapars-0.2.6.dist-info/entry_points.txt
frapars-0.2.6.dist-info/RECORD
