Metadata-Version: 2.1
Name: frapars
Version: 0.2.6
Summary: Simple script that permits to parse addresses in France format.
Home-page: https://github.com/ieCecchetti/frapars
License: MIT
Author: Enrico Cecchetti
Author-email: enrico.cecchetti@kcitylabs.fr
Requires-Python: >=3.9,<4.0
Classifier: Development Status :: 4 - Beta
Classifier: Intended Audience :: Developers
Classifier: License :: OSI Approved :: MIT License
Classifier: Programming Language :: Python :: 3
Classifier: Programming Language :: Python :: 3.9
Classifier: Programming Language :: Python :: 3.10
Classifier: Programming Language :: Python :: 3.11
Classifier: Programming Language :: Python :: 3.12
Requires-Dist: chardet (>=5.2.0,<6.0.0)
Requires-Dist: pandas (>=2.2.1,<3.0.0)
Requires-Dist: ptvsd (>=4.3.2,<5.0.0)
Requires-Dist: pytest (>=8.1.1,<9.0.0)
Requires-Dist: requests (>=2.31.0,<3.0.0)
Requires-Dist: tqdm (>=4.66.2,<5.0.0)
Project-URL: Repository, https://github.com/ieCecchetti/frapars
